<?xml version="1.0" encoding="UTF-8"?>
<!-- 
    Allku Pos  - Touch Friendly Point Of Sale
    Copyright (c) 2009-2018 uniCenta & previous Openbravo POS works
    https://www.allku.expert

    This file is part of Allku Pos

    Allku Pos is free software: you can redistribute it and/or modify
    it under the terms of the GNU General Public License as published by
    the Free Software Foundation, either version 3 of the License, or
    (at your option) any later version.

    Allku Pos is distributed in the hope that it will be useful,
    but WITHOUT ANY WARRANTY; without even the implied warranty of
    MERCHANTABILITY or FITNESS FOR A PARTICULAR PURPOSE.  See the
    GNU General Public License for more details.

    You should have received a copy of the GNU General Public License
    along with Allku Pos.  If not, see <http://www.gnu.org/licenses/>.
 -->

<output>

    <display>
        <line><text align="left" length="8">Total</text><text align="right" length="12">${ticket.printTotal()}</text></line>
        <line><text align="center" length="20">Thank you</text></line>
    </display>
    
    #foreach ($paymentline in $ticket.payments)
    #if ($paymentline.name == "cash")
    <opendrawer/>
    #end
    #if ($paymentline.name == "cashrefund")
    <opendrawer/>
    #end
    #end

    <ticket>
        <!--<image>Printer.Ticket.Logo</image>-->
        <line>
        </line>
        <line>
            <text align="center" length="40">${ticket.getTaxpayerInfo().getComercialName()}</text>
        </line>
        <line>
            <text align="center" length="40">${ticket.getTaxpayerInfo().getLegalName()}</text>
        </line>
        <line>
            <text align="center" length="40">RUC ${ticket.getTaxpayerInfo().getIdentification()}</text>
        </line>
        #if (${ticket.printForcedAccounting()} != "")
        <line>
            <text align="center" length="40">${ticket.printForcedAccounting()}</text>
        </line>
        #end
        #if (${ticket.printSpecialTaxpayer()} != "")
        <line>
            <text align="center" length="40">${ticket.printSpecialTaxpayer()}</text>
        </line>
        #end
        #if (${ticket.printMicroBusiness()} != "")
        <line>
            <text align="center" length="40">${ticket.printMicroBusiness()}</text>
        </line>
        #end
        #if (${ticket.printRetentionAgent()} != "")
        <line>
            <text align="center" length="40">${ticket.printRetentionAgent()}</text>
        </line>
        #end
        #if (${ticket.getTaxpayerInfo().getAddress()} != "")                        
        <line>
            <text align="center" length="40">${ticket.getTaxpayerInfo().getAddress()}</text>
        </line>
        #end
        #if (${ticket.getTaxpayerInfo().getPhone()} != "")
        <line>
            <text align="center" length="40">${ticket.getTaxpayerInfo().getPhone()}</text>
        </line>
        #end
        #if (${ticket.getTaxpayerInfo().geteMail()} != "")
        <line>
            <text align="center" length="40">${ticket.getTaxpayerInfo().geteMail()}</text>
        </line>
        #end
        <line>
            <text>Clave de acceso: ${ticket.printClaveAcceso()}</text>
        </line>        
        <line>
            <text align="center" length="40">      - - - - - - - - - - - - -      </text>
        </line>
        <line>
            <text align="center" length="40">${ticket.printAmbiente()}</text>
        </line>

        <!--<line><text align="center" length="40">Printer.Ticket</text></line>-->

        #if (${ticket.ticketType} == 0)
        <line>
            <text align="left" length="40">Factura: ${ticket.printSecuencial()}</text>
        </line>
        #end
        #if (${ticket.ticketType} == 1)
        <line>
            <text align="left" length="40">Nota de Crédito: ${ticket.printSecuencial()}</text>
        </line>
        #end

        <line>
            <text align="left" length="40">Fecha: ${ticket.printDate()}</text>
        </line>

        #if ($ticket.getCustomer())
        <line>
            <text align="left" length="40">Identificación: ${ticket.getCustomer().printTaxCustomerID()}</text>
        </line>
        <line>
            <text align="left" length="40">Cliente: ${ticket.getCustomer().printName()}</text>
        </line>
        <line>
            <text align="left" length="40">Dirección: ${ticket.getCustomer().printAddress()}</text>
        </line>                
        #end

        #if (${tickettext.place} != ${place})
        <line><text align="left" length="15">Mesa:</text><text>${place}</text></line>
        #end
        <line>
            <text align ="left" length="16">Producto</text>
            <text align ="right" length="8">Precio</text>
            <text align ="right" length="5"></text>
            <text align ="right" length="9">Valor</text>
        </line>
        <line>
            <text align="left" length="40">- - - - - - - - - - - - - - - - - - - -</text>
        </line>
        
        #foreach ($ticketline in $ticket.getLines())
        <line>
            #if ($ticketline.isProductCom())
            <text align ="left" length="17">*${ticketline.printName()}</text>
            #else
            <text align ="left" length="17">${ticketline.printName()}</text>
            #end
            <!-- Print line to show Prices pre-Tax
                        <text align ="right" length="8">${ticketline.printPrice()}</text>
                        <text align ="right" length="7">x${ticketline.printMultiply()}</text>
                        <text align ="right" length="8">${ticketline.printSubValue()}</text>
                     </line>
            -->

            <!-- Print line to show Prices inc. Tax -->
            <text align ="right" length="8">${ticketline.printPrice()}</text>
            <text align ="right" length="5">x${ticketline.printMultiply()}</text>
            <text align ="right" length="8">${ticketline.printSubValue()}</text>
            <text align ="right" length="2">${ticketline.printConIVA()}</text>
        </line>

        <!-- un-comment line below if you want to add a product's properties -->
        <!-- <line><text align ="left" length="40">${ticketline.getProperty("ingredients", "")}</text> </line> -->

        <!-- un-comment line below if you want to add a user input sales line's Note -->
        <!-- <line><text align ="left" length="40">${ticketline.getProperty("notes", "")}</text> </line> -->

        <!-- un-comment line below if you want to add a product's barcode -->
        <!-- <line><text align ="left" length="12">Barcode :   </text>${ticketline.printCode()}</text></line> -->

        <!-- un-comment line below if you want to add a product's Reference -->
        <!-- <line><text align ="left" length="12">Reference : </text>${ticketline.printReference()}</text></line> -->

        #if ($ticketline.productAttSetInstId)
        <line>
            <text align ="left" length="40">${ticketline.productAttSetInstDesc}</text>
        </line>
        #end
        #end

        <line>
            <text align="left" length="40">- - - - - - - - - - - - - - - - - - - -</text>
        </line>
        <line>
            <text>Productos: </text>
            <text align ="left" length="14">${ticket.printArticlesCount()}</text>
        </line>
        <line>
            <text align ="left" length="16">Subtotal</text>
            <text align ="right" length="24">${ticket.printSubTotal()}</text>
        </line>        

        #foreach ($taxinfo in $taxes)
        #set( $taxline = $ticket.getTaxLine($taxinfo))
        <line>
            <text align ="left" length="16">${taxline.printTaxInfo()}</text>
            <text align ="right" length="24">${taxline.printSubTotal()}</text>
        </line>
        #end
        <line>
            <text align ="left" length="16">IVA 12%</text>
            <text align ="right" length="24">${ticket.printTax()}</text>
        </line>
        <line size="1">
            <text align ="left" length="16" bold="true">Total</text>
            <text align ="right" length="24" bold="true">${ticket.printTotal()}</text>
        </line>

        #foreach ($paymentline in $ticket.payments)
        #if ($paymentline.name == "cash")
        <line>
            <text bold="true">Efectivo</text>
        </line>
        <line>
            <text align="left" length="20">Entregado:</text>
            <text align ="right" length="20">${paymentline.printPaid()}</text>
        </line>
        <line>
            <text align="left" length="20">Cambio:</text>
            <text align ="right" length="20">${paymentline.printChange()}</text>
        </line>
        #end

        #if ($paymentline.name == "cashrefund")
        <line>
            <text align="left" length="20" bold="true">Devuelto</text>
            <text align ="right" length="20">${paymentline.printPaid()}</text>
        </line>
        #end
        #if ($paymentline.name == "cheque")
        <line>
            <text align="left" length="20" bold="true">Cheque</text>
            <text align ="right" length="20">${paymentline.printPaid()}</text>
        </line>
        #end
        #if ($paymentline.name == "chequerefund")
        <line>
            <text align="left" length="20" bold="true">Cheque devuelto</text>
            <text align ="right" length="20">${paymentline.printPaid()}</text>
        </line>
        #end
        #if ($paymentline.name == "voucherin")
        <line>
            <text align="left" length="20" bold="true">Voucher : ${paymentline.printVoucherNumber()}</text>
            <text align ="right" length="20">${paymentline.printPaid()}</text>
        </line>
        #end
        #if ($paymentline.name == "voucherout")
        <line>
            <text align="left" length="20" bold="true">Voucher devuelto : ${paymentline.printVoucherNumber()}</text>
            <text align ="right" length="20">${paymentline.printPaid()}</text>
        </line>
        #end
        #if ($paymentline.name == "slip")
        <line>
            <text align="left" length="20" bold="true">Regalo</text>
            <text align ="right" length="20">${paymentline.printPaid()}</text>
        </line>
        #end
        #if ($paymentline.name == "free")
        <line>
            <text align="left" length="20" bold="true">Gratis</text>
            <text align ="right" length="20">${paymentline.printPaid()}</text>
        </line>
        #end
        #if ($paymentline.name == "debt")
        <line>
            <text align="left" length="20" bold="true">Crédito</text>
            <text align ="right" length="20">${paymentline.printPaid()}</text>
        </line>
        #end
        #end

        #if (${ticket.printTicketFooterLine1()} != "")
        <line></line>
        <line>
            <text align="center" length="40">${ticket.printTicketFooterLine1()}</text>
        </line>
        #end
        #if (${ticket.printTicketFooterLine2()} != "")
        <line>
            <text>${ticket.printTicketFooterLine2()}</text>
        </line>
        #end
        #if (${ticket.printTicketFooterLine3()} != "")
        <line>
            <text>${ticket.printTicketFooterLine3()}</text>
        </line>
        #end
        #if (${ticket.printTicketFooterLine4()} != "")
        <line>
            <text>${ticket.printTicketFooterLine4()}</text>
        </line>
        #end
        #if (${ticket.printTicketFooterLine5()} != "")
        <line>
            <text>${ticket.printTicketFooterLine5()}</text>
        </line>
        #end
        #if (${ticket.printTicketFooterLine6()} != "")
        <line>
            <text>${ticket.printTicketFooterLine6()}</text>
        </line>
        #end
        <line></line>

        #foreach ($paymentline in $ticket.payments)

        #if ($paymentline.name == "ccard")
        #if ($paymentline.chipAndPin)
        <line size="1">
            <text align="center" length="40" bold="true">CARD SALE</text>
        </line>
        <line size="1">
            <text>${paymentline.getCardName()}</text>
        </line>
        <line><text>${paymentline.printCardNumber()}</text></line>
        <line></line>
        <line size="1">
            <text align="left" length="10">AMOUNT</text>
            <text align ="right" length="30">${paymentline.printTotal()}</text>
        </line>
        <line>
            <text>Tranx ID        : </text>
            <text>${paymentline.printTransactionID()}</text>
        </line>
        <line>
            <text>Auth Code       : </text>
            <text>${paymentline.printAuthorization()}</text>
        </line>
        <line>
            <text>Verified By     : </text>
            <text>${paymentline.printVerification()}</text>
        </line>
        <line>
            <text>Card # (last 4) : </text>
            <text>${paymentline.printLastFourDigits()}</text>
        </line>
        #end
        #if (!$paymentline.chipAndPin)
        <line size="1">
            <text align="center" length="40" bold="true">CARD SALE</text>
        </line>
        <line size="1"><text>${paymentline.getCardName()}</text></line>
        <line>
            <text>${paymentline.printCardNumber()}</text>
        </line>
        <line></line>
        <line size="1">
            <text align="left" length="10">AMOUNT</text>
            <text align ="right" length="30">${paymentline.printTotal()}</text>
        </line>
        <line>
            <text align ="left" length="20">Expiration Date:</text>
            <text>${paymentline.printExpirationDate()}</text>
        </line>
        <line>
            <text>Operation : </text>
            <text>${paymentline.printTransactionID()}</text>
        </line>
        <line>
            <text>Auth Code : </text>
            <text>${paymentline.printAuthorization()}</text>
        </line>
        <line></line>
        #end
        #if ($ticket.hasTip())
        <line>
            <text align ="left" length="15">Tip:</text>
            <text align ="right" length="25">_______________</text>
        </line>
        <line></line>
        <line size="1">
            <text align ="left" length="15" bold="false">Total</text>
            <text align ="right" length="25" bold="false">_______________</text>
        </line>
        <line></line>
        <line></line>
        <line size="1">
            <text align ="left" length="40" bold="false">__________________________________________</text>
        </line>
        <line size="1">
            <text align ="center" length="40" bold="false">Signature</text>
        </line>
        #else
        <line size="1">
            <text align ="left" length="15" bold="true">Total</text>
            <text align ="right" length="25" bold="true">${paymentline.printTotal()}</text>
        </line>
        #end
        #end
        #if ($paymentline.name == "ccardrefund")
        <line size="1">
            <text align="center" length="40" bold="true">CARD REFUND</text>
        </line>
        <line size="1">
            <text>${paymentline.getCardName()}</text>
        </line>
        <line><text>${paymentline.printCardNumber()}</text></line>
        <line></line>
        <line size="1">
            <text align="left" length="10">AMOUNT</text>
            <text align ="right" length="30">${paymentline.printTotal()}</text>
        </line>
        <line>
            <text align ="left" length="20">Expiration Date:</text>
            <text>${paymentline.printExpirationDate()}</text>
        </line>
        <line>
            <text>Tranx ID  : </text>
            <text>${paymentline.printTransactionID()}</text>
        </line>
        <line>
            <text>Auth Code : </text>
            <text>${paymentline.printAuthorization()}</text>
        </line>
        <line></line>
        #end
        #end

<!--        <line>
            <text align="left" length="40">Terminal: ${ticket.getHost()}</text>
        </line>
        <line>
            <text align="left" length="40">Atendido por: ${ticket.printUser()}</text>
        </line>-->
    </ticket>
</output>